{
    "text": "Given what Musk is doing now, do you think the internet will still be here in a year? Will there be any tech companies that aren't wholly owned by Musk, Inc. Will owning things even mean anything? Or is this the beginning of the rule of the tech bros, world wide. I can't imagine what they're planning for us. In the meantime, me divesting my Tesla, which seemed so urgent just 24 hours ago, now seems like a powerless gesture. I heard it said that now feels like the moment in Covid when you realized everything was about to freeze, and you'd better head to the supermarket right now, and when you got there, you found you weren't among the first to see it this way. I was very reassured by the blog post that Krugman did. It's nice to hear a sane voice out there. ",
    "created": "Sat, 01 Feb 2025 16:40:38 GMT",
    "type": "outline",
    "image": "https://imgs.scripting.com/2023/03/20/mrSmith.png",
    "flInCalendar": true
}