{
    "text": "Google Reader is dead",
    "created": "Sat, 21 Dec 2019 17:00:42 GMT",
    "type": "outline",
    "subs": [
        {
            "text": "A new <a href=\"https://mcfunley.com/google-reader-killed-rss\">empassioned piece</a> about \"RSS\" and <a href=\"https://www.google.com/search?q=site%3Ascripting.com+%22google+reader%22\">Google Reader</a> goes over the top, accusing Google of murdering RSS, when RSS is out and about, earning a good living providing news to millions of people. It certainly isn't <a href=\"http://thesaurus.land/?word=dead\">what</a> Mr McKinley says it is. But I do appreciate the sentiment. He's right that people are crazy when they miss Google Reader, it's like missing the pet fox your friend let sleep in your hen house. Google was very bad news for RSS. ",
            "created": "Sat, 21 Dec 2019 17:00:51 GMT",
            "image": "http://scripting.com/images/2019/12/21/fox.png"
        },
        {
            "text": "Then I started thinking of other things Google Reader is like.",
            "created": "Sat, 21 Dec 2019 17:02:58 GMT",
            "flBulletedSubs": "true",
            "subs": [
                {
                    "text": "An oil spill by Exxon in virgin Alaskan wilderness. ",
                    "created": "Sat, 21 Dec 2019 17:03:14 GMT"
                },
                {
                    "text": "A nuclear meltdown in the city you live in a suburb of.",
                    "created": "Sat, 21 Dec 2019 17:03:33 GMT"
                },
                {
                    "text": "A neighbor who runs a crack factory down the block from an elementary school.",
                    "created": "Sat, 21 Dec 2019 17:03:48 GMT"
                }
            ]
        },
        {
            "text": "I may add items to the list. ",
            "created": "Sat, 21 Dec 2019 17:04:08 GMT"
        },
        {
            "text": "It's fun to hate Google Reader, but it's over my friend, and we are free to do whatever we like. Enjoy the holidays knowing that Google Reader is dead, RSS is fine.",
            "created": "Sat, 21 Dec 2019 17:09:26 GMT"
        }
    ]
}