{
    "text": "If the US govt were Facebook",
    "created": "Tue, 18 Dec 2018 15:28:15 GMT",
    "type": "outline",
    "description": "What if we expected as much from the government as we do of tech icons?",
    "subs": [
        {
            "text": "If the US govt were a software company we'd all be quitting them. ",
            "created": "Tue, 18 Dec 2018 15:28:22 GMT"
        },
        {
            "text": "Imagine this. I signed up for Obamacare in 2012. It was great. ",
            "created": "Tue, 18 Dec 2018 15:28:56 GMT"
        },
        {
            "text": "Call that version 1.0. ",
            "created": "Tue, 18 Dec 2018 15:30:30 GMT"
        },
        {
            "text": "Now six years later, I'm still alive, I've paid in many tens of thousands into it, and drawn out much less, even though I have a pre-existing condition or two. ",
            "created": "Tue, 18 Dec 2018 15:29:04 GMT"
        },
        {
            "text": "What have they done?"
        },
        {
            "text": "They're removing features not adding them. And threatening to deprecate the whole thing. Every damn year there's some government-made crisis that threatens to put me at risk of needing some urgent and super-expensive health care <i>without insurance. </i>I'm happy to pay, it's worth it, but this really sucks! ",
            "created": "Tue, 18 Dec 2018 15:31:08 GMT"
        },
        {
            "text": "I'd quit, except it's the only health insurance I can get. ",
            "created": "Tue, 18 Dec 2018 15:31:17 GMT"
        },
        {
            "text": "So I can't."
        }
    ]
}