{
    "text": "BTW, there's a new <a href=\"https://github.com/scripting/pagePark#v0820-7521-by-dw\">version</a> of PagePark, v0.8.20, that has the feature described in the <a href=\"https://github.com/scripting/pagePark/issues/19\">RFC from Friday</a>. It makes it a bit simpler to set up a Glitch server, for example, for people who are new to PP.",
    "created": "Mon, 05 Jul 2021 16:10:48 GMT",
    "type": "outline",
    "image": "http://scripting.com/images/2021/07/05/fridaBarbie.png",
    "imageLink": "https://www.walmart.com/ip/Barbie-Inspiring-Women-Series-Frida-Kahlo-Doll-Iconic-Fringe-Shawl/753705253?wmlspartner=wlpa&selectedSellerId=8984&&adid=22222222227128497662&wl0=&wl1=g&wl2=c&wl3=235177691734&wl4=aud-1319366384141:pla-388260369501&wl5=1023511&wl6=&wl7=&wl8=&wl9=pla&wl10=115786543&wl11=online&wl12=753705253&veh=sem&gclid=Cj0KCQjw24qHBhCnARIsAPbdtlLTXWMGhGCgRjuYY7pxeG1w5s-w5HV7sKSZgk0QYanAcz9KSBVWBdgaAk2LEALw_wcB&gclsrc=aw.ds",
    "flInCalendar": true
}